{
  "label": "raw",
  "results": {
    "LogReg": {
      "full": {
        "per_class": {
          "crisis": {
            "precision": 0.2154,
            "recall": 0.4118,
            "f1": 0.2828,
            "roc_auc": 0.6306,
            "support": 68
          },
          "neither": {
            "precision": 0.8433,
            "recall": 0.5901,
            "f1": 0.6943,
            "roc_auc": 0.6923,
            "support": 383
          },
          "recovery": {
            "precision": 0.1869,
            "recall": 0.3704,
            "f1": 0.2484,
            "roc_auc": 0.6366,
            "support": 54
          }
        },
        "macro": {
          "precision": 0.4152,
          "recall": 0.4574,
          "f1": 0.4085,
          "roc_auc": 0.6532
        },
        "weighted": {
          "precision": 0.6885,
          "recall": 0.5426,
          "f1": 0.5912
        }
      },
      "high_conf": {
        "per_class": {
          "crisis": {
            "precision": 0.2917,
            "recall": 0.5147,
            "f1": 0.3723,
            "roc_auc": 0.6478,
            "support": 68
          },
          "neither": {
            "precision": 0.8871,
            "recall": 0.5744,
            "f1": 0.6973,
            "roc_auc": 0.6725,
            "support": 383
          },
          "recovery": {
            "precision": 0.0741,
            "recall": 0.32,
            "f1": 0.1203,
            "roc_auc": 0.4999,
            "support": 25
          }
        },
        "macro": {
          "precision": 0.4176,
          "recall": 0.4697,
          "f1": 0.3966,
          "roc_auc": 0.6067
        },
        "weighted": {
          "precision": 0.7593,
          "recall": 0.5525,
          "f1": 0.6206
        }
      }
    },
    "RandForest": {
      "full": {
        "per_class": {
          "crisis": {
            "precision": 0.25,
            "recall": 0.0441,
            "f1": 0.075,
            "roc_auc": 0.659,
            "support": 68
          },
          "neither": {
            "precision": 0.7794,
            "recall": 0.9687,
            "f1": 0.8638,
            "roc_auc": 0.7079,
            "support": 383
          },
          "recovery": {
            "precision": 0.2941,
            "recall": 0.0926,
            "f1": 0.1408,
            "roc_auc": 0.6616,
            "support": 54
          }
        },
        "macro": {
          "precision": 0.4412,
          "recall": 0.3685,
          "f1": 0.3599,
          "roc_auc": 0.6762
        },
        "weighted": {
          "precision": 0.6562,
          "recall": 0.7505,
          "f1": 0.6803
        }
      },
      "high_conf": {
        "per_class": {
          "crisis": {
            "precision": 0.4286,
            "recall": 0.0441,
            "f1": 0.08,
            "roc_auc": 0.6569,
            "support": 68
          },
          "neither": {
            "precision": 0.8081,
            "recall": 0.9896,
            "f1": 0.8897,
            "roc_auc": 0.6641,
            "support": 383
          },
          "recovery": {
            "precision": 0.0,
            "recall": 0.0,
            "f1": 0.0,
            "roc_auc": 0.4885,
            "support": 25
          }
        },
        "macro": {
          "precision": 0.4122,
          "recall": 0.3446,
          "f1": 0.3232,
          "roc_auc": 0.6032
        },
        "weighted": {
          "precision": 0.7114,
          "recall": 0.8025,
          "f1": 0.7273
        }
      }
    }
  },
  "feature_importance": {
    "feature": [
      "ttr_baseline",
      "sentiment_mean_baseline",
      "sentiment_mean_pre_4w",
      "ttr_delta_pre_4w",
      "fp_pronoun_rate_baseline",
      "avg_sent_len_baseline",
      "avg_post_len_baseline",
      "avg_sent_len_delta_pre_4w",
      "sentiment_mean_pre_2w",
      "sentiment_mean_delta_pre_4w",
      "fp_pronoun_rate_delta_pre_4w",
      "post_freq_baseline",
      "ttr_pre_4w",
      "sentiment_mean_delta_pre_2w",
      "post_freq_delta_pre_4w"
    ],
    "importance": [
      0.058122,
      0.039922,
      0.03485,
      0.03374,
      0.029062,
      0.027927,
      0.027856,
      0.027294,
      0.026692,
      0.026403,
      0.025369,
      0.02504,
      0.024691,
      0.024119,
      0.023377
    ]
  }
}